catfacts/__init__.py
catfacts/main.py
catfacts/cats/1.txt
catfacts/cats/10.txt
catfacts/cats/11.txt
catfacts/cats/12.txt
catfacts/cats/13.txt
catfacts/cats/14.txt
catfacts/cats/15.txt
catfacts/cats/16.txt
catfacts/cats/17.txt
catfacts/cats/2.txt
catfacts/cats/3.txt
catfacts/cats/4.txt
catfacts/cats/5.txt
catfacts/cats/6.txt
catfacts/cats/7.txt
catfacts/cats/8.txt
catfacts/cats/9.txt
catfacts_demo-0.1.2.dist-info/METADATA
catfacts_demo-0.1.2.dist-info/WHEEL
catfacts_demo-0.1.2.dist-info/entry_points.txt
catfacts_demo-0.1.2.dist-info/top_level.txt
catfacts_demo-0.1.2.dist-info/RECORD
