Metadata-Version: 2.4
Name: catfacts-demo
Version: 0.1.2
Summary: Display cat facts
Requires-Python: >=3.13
Requires-Dist: pydantic>=2.11.9
Requires-Dist: pydantic-settings>=2.11.0
Requires-Dist: requests>=2.32.5
Requires-Dist: rich>=14.1.0
